{
  "events": [
    {
      "identifier": "mb90143723",
      "authority": "MB",
      "eventType": "eq",
      "originTimeUtc": 1780554570.23,
      "latitudeDeg": 44.7488333333333,
      "longitudeDeg": -111.236333333333,
      "depthKm": 7.3,
      "magnitude": -0.23,
      "isLocal": false,
      "nearestTown": null,
      "version": null
    },
    {
      "identifier": "mb90143733",
      "authority": "MB",
      "eventType": "eq",
      "originTimeUtc": 1780591421.33,
      "latitudeDeg": 44.7255,
      "longitudeDeg": -112.413166666667,
      "depthKm": 3.71,
      "magnitude": 1.05,
      "isLocal": false,
      "nearestTown": null,
      "version": null
    },
    {
      "identifier": "uu80141446",
      "authority": "UU",
      "eventType": "eq",
      "originTimeUtc": 1780394101.77,
      "latitudeDeg": 41.56066666666667,
      "longitudeDeg": -112.3895,
      "depthKm": 0.3,
      "magnitude": 1.1,
      "isLocal": true,
      "nearestTown": "{'town': 'Penrose, UT', 'bearing': 'SW', 'distanceKM': 12.564240331238201}",
      "version": null
    },
    {
      "identifier": "uu80141496",
      "authority": "UU",
      "eventType": "eq",
      "originTimeUtc": 1780457158.5900002,
      "latitudeDeg": 41.73766666666667,
      "longitudeDeg": -111.72616666666667,
      "depthKm": 9.37,
      "magnitude": 1.27,
      "isLocal": true,
      "nearestTown": "{'town': 'North Logan, UT', 'bearing': 'ESE', 'distanceKM': 7.408835241120995}",
      "version": null
    },
    {
      "identifier": "uu80141031",
      "authority": "UU",
      "eventType": "eq",
      "originTimeUtc": 1779689983.6699982,
      "latitudeDeg": 38.491166666666665,
      "longitudeDeg": -112.90233333333333,
      "depthKm": 3.73,
      "magnitude": 1.18,
      "isLocal": true,
      "nearestTown": "{'town': 'Milford, UT', 'bearing': 'NE', 'distanceKM': 14.110447533953133}",
      "version": null
    },
    {
      "identifier": "uu80141441",
      "authority": "UU",
      "eventType": "eq",
      "originTimeUtc": 1780388749.6499977,
      "latitudeDeg": 39.0095,
      "longitudeDeg": -111.39183333333334,
      "depthKm": -0.88,
      "magnitude": 1.61,
      "isLocal": true,
      "nearestTown": "{'town': 'Emery, UT', 'bearing': 'NW', 'distanceKM': 15.666287197310856}",
      "version": null
    },
    {
      "identifier": "uu80141151",
      "authority": "UU",
      "eventType": "eq",
      "originTimeUtc": 1779861024.369999,
      "latitudeDeg": 37.17166666666667,
      "longitudeDeg": -113.40516666666667,
      "depthKm": 7.6,
      "magnitude": 1.51,
      "isLocal": true,
      "nearestTown": "{'town': 'Leeds, UT', 'bearing': 'SSW', 'distanceKM': 8.487530588038592}",
      "version": null
    },
    {
      "identifier": "uu80141146",
      "authority": "UU",
      "eventType": "eq",
      "originTimeUtc": 1779860834.63,
      "latitudeDeg": 38.5095,
      "longitudeDeg": -112.911,
      "depthKm": 2.63,
      "magnitude": 1.0,
      "isLocal": true,
      "nearestTown": "{'town': 'Milford, UT', 'bearing': 'NE', 'distanceKM': 15.24099173385414}",
      "version": null
    },
    {
      "identifier": "uu80141161",
      "authority": "UU",
      "eventType": "eq",
      "originTimeUtc": 1779879338.1299973,
      "latitudeDeg": 41.861666666666665,
      "longitudeDeg": -111.497,
      "depthKm": 10.24,
      "magnitude": 1.1300000000000001,
      "isLocal": true,
      "nearestTown": "{'town': 'Garden City, UT', 'bearing': 'SW', 'distanceKM': 12.774600268670508}",
      "version": null
    },
    {
      "identifier": "uu80141591",
      "authority": "UU",
      "eventType": "eq",
      "originTimeUtc": 1780629888.7399979,
      "latitudeDeg": 38.85783333333333,
      "longitudeDeg": -111.47,
      "depthKm": 3.19,
      "magnitude": 0.93,
      "isLocal": true,
      "nearestTown": "{'town': 'Emery, UT', 'bearing': 'WSW', 'distanceKM': 20.46995354433598}",
      "version": null
    },
    {
      "identifier": "us7000sr5g",
      "authority": "US",
      "eventType": "eq",
      "originTimeUtc": 1780784554.241,
      "latitudeDeg": 45.6697,
      "longitudeDeg": -112.2403,
      "depthKm": 8.57,
      "magnitude": 2.9,
      "isLocal": false,
      "nearestTown": null,
      "version": null
    },
    {
      "identifier": "uu80141286",
      "authority": "UU",
      "eventType": "eq",
      "originTimeUtc": 1780058215.6699982,
      "latitudeDeg": 44.801,
      "longitudeDeg": -110.817,
      "depthKm": 4.52,
      "magnitude": 1.3,
      "isLocal": true,
      "nearestTown": "{'town': 'Mammoth, WY', 'bearing': 'SSW', 'distanceKM': 21.48583645739887}",
      "version": null
    },
    {
      "identifier": "uu80141246",
      "authority": "UU",
      "eventType": "eq",
      "originTimeUtc": 1780001161.1799998,
      "latitudeDeg": 44.793,
      "longitudeDeg": -110.825,
      "depthKm": 4.84,
      "magnitude": 1.41,
      "isLocal": true,
      "nearestTown": "{'town': 'Mammoth, WY', 'bearing': 'SSW', 'distanceKM': 22.558174999546853}",
      "version": null
    },
    {
      "identifier": "mb90143888",
      "authority": "MB",
      "eventType": "eq",
      "originTimeUtc": 1780697778.92,
      "latitudeDeg": 44.6506666666667,
      "longitudeDeg": -112.149,
      "depthKm": 3.18,
      "magnitude": 1.31,
      "isLocal": false,
      "nearestTown": null,
      "version": null
    },
    {
      "identifier": "uu80141351",
      "authority": "UU",
      "eventType": "eq",
      "originTimeUtc": 1780185538.6499977,
      "latitudeDeg": 38.08583333333333,
      "longitudeDeg": -112.48116666666667,
      "depthKm": -0.87,
      "magnitude": 2.06,
      "isLocal": true,
      "nearestTown": "{'town': 'Spry, UT', 'bearing': 'NW', 'distanceKM': 12.408696805143293}",
      "version": null
    },
    {
      "identifier": "nn00919723",
      "authority": "NN",
      "eventType": "eq",
      "originTimeUtc": 1780570269.339,
      "latitudeDeg": 37.2186,
      "longitudeDeg": -114.6815,
      "depthKm": 8.4467,
      "magnitude": 1.7,
      "isLocal": false,
      "nearestTown": null,
      "version": null
    },
    {
      "identifier": "uu80141326",
      "authority": "UU",
      "eventType": "eq",
      "originTimeUtc": 1780160505.2399979,
      "latitudeDeg": 39.27433333333333,
      "longitudeDeg": -111.27533333333334,
      "depthKm": 0.16,
      "magnitude": 2.07,
      "isLocal": true,
      "nearestTown": "{'town': 'Orangeville, UT', 'bearing': 'WNW', 'distanceKM': 19.807481216619415}",
      "version": null
    },
    {
      "identifier": "uu80141556",
      "authority": "UU",
      "eventType": "eq",
      "originTimeUtc": 1780594802.71,
      "latitudeDeg": 37.55466666666667,
      "longitudeDeg": -113.05466666666666,
      "depthKm": 10.15,
      "magnitude": 1.59,
      "isLocal": true,
      "nearestTown": "{'town': 'Hamiltons Fort, UT', 'bearing': 'SE', 'distanceKM': 10.85601722296789}",
      "version": null
    },
    {
      "identifier": "mb90143123",
      "authority": "MB",
      "eventType": "eq",
      "originTimeUtc": 1780285543.65,
      "latitudeDeg": 45.724,
      "longitudeDeg": -111.349,
      "depthKm": 11.6,
      "magnitude": 1.13,
      "isLocal": false,
      "nearestTown": null,
      "version": null
    },
    {
      "identifier": "mb90143728",
      "authority": "MB",
      "eventType": "eq",
      "originTimeUtc": 1780571704.04,
      "latitudeDeg": 44.9261666666667,
      "longitudeDeg": -112.261666666667,
      "depthKm": 5.0,
      "magnitude": 0.72,
      "isLocal": false,
      "nearestTown": null,
      "version": null
    },
    {
      "identifier": "mb90143838",
      "authority": "MB",
      "eventType": "eq",
      "originTimeUtc": 1780717880.57,
      "latitudeDeg": 44.7596666666667,
      "longitudeDeg": -111.914833333333,
      "depthKm": 12.27,
      "magnitude": 2.28,
      "isLocal": false,
      "nearestTown": null,
      "version": null
    },
    {
      "identifier": "mb90142898",
      "authority": "MB",
      "eventType": "eq",
      "originTimeUtc": 1780221305.25,
      "latitudeDeg": 44.7735,
      "longitudeDeg": -111.378,
      "depthKm": 10.68,
      "magnitude": 0.5,
      "isLocal": false,
      "nearestTown": null,
      "version": null
    },
    {
      "identifier": "uu80141251",
      "authority": "UU",
      "eventType": "eq",
      "originTimeUtc": 1780001935.4199982,
      "latitudeDeg": 41.861666666666665,
      "longitudeDeg": -112.7755,
      "depthKm": 3.42,
      "magnitude": 3.1,
      "isLocal": true,
      "nearestTown": "{'town': 'Snowville, UT', 'bearing': 'SSW', 'distanceKM': 12.765137599458305}",
      "version": null
    },
    {
      "identifier": "mb90143373",
      "authority": "MB",
      "eventType": "eq",
      "originTimeUtc": 1780394611.98,
      "latitudeDeg": 44.8713333333333,
      "longitudeDeg": -111.5025,
      "depthKm": 12.69,
      "magnitude": 0.13,
      "isLocal": false,
      "nearestTown": null,
      "version": null
    },
    {
      "identifier": "uu80141451",
      "authority": "UU",
      "eventType": "eq",
      "originTimeUtc": 1780405095.2299995,
      "latitudeDeg": 36.945166666666665,
      "longitudeDeg": -112.58666666666667,
      "depthKm": 20.72,
      "magnitude": 1.31,
      "isLocal": true,
      "nearestTown": "{'town': 'Fredonia, AZ', 'bearing': 'W', 'distanceKM': 5.338134605124}",
      "version": null
    },
    {
      "identifier": "uu80141136",
      "authority": "UU",
      "eventType": "eq",
      "originTimeUtc": 1779852022.5699997,
      "latitudeDeg": 37.170833333333334,
      "longitudeDeg": -113.4055,
      "depthKm": 8.23,
      "magnitude": 1.56,
      "isLocal": true,
      "nearestTown": "{'town': 'Leeds, UT', 'bearing': 'SSW', 'distanceKM': 8.58300720543952}",
      "version": null
    },
    {
      "identifier": "uu80141401",
      "authority": "UU",
      "eventType": "eq",
      "originTimeUtc": 1780293935.2599983,
      "latitudeDeg": 41.6925,
      "longitudeDeg": -112.62066666666666,
      "depthKm": 5.03,
      "magnitude": 1.92,
      "isLocal": true,
      "nearestTown": "{'town': 'Howell, UT', 'bearing': 'SW', 'distanceKM': 18.609428014778846}",
      "version": null
    },
    {
      "identifier": "uu80141026",
      "authority": "UU",
      "eventType": "eq",
      "originTimeUtc": 1779688160.33,
      "latitudeDeg": 41.866,
      "longitudeDeg": -112.76083333333334,
      "depthKm": 0.72,
      "magnitude": 1.92,
      "isLocal": true,
      "nearestTown": "{'town': 'Snowville, UT', 'bearing': 'SSW', 'distanceKM': 11.845277526120839}",
      "version": null
    },
    {
      "identifier": "nn00919726",
      "authority": "NN",
      "eventType": "eq",
      "originTimeUtc": 1780573683.339,
      "latitudeDeg": 37.4182,
      "longitudeDeg": -114.3917,
      "depthKm": 14.112,
      "magnitude": 1.76,
      "isLocal": false,
      "nearestTown": null,
      "version": null
    },
    {
      "identifier": "nn00919822",
      "authority": "NN",
      "eventType": "eq",
      "originTimeUtc": 1780748379.124,
      "latitudeDeg": 37.2298,
      "longitudeDeg": -114.5851,
      "depthKm": 11.8556,
      "magnitude": 1.6,
      "isLocal": false,
      "nearestTown": null,
      "version": null
    },
    {
      "identifier": "us6000t049",
      "authority": "US",
      "eventType": "eq",
      "originTimeUtc": 1779737914.683,
      "latitudeDeg": 44.8401,
      "longitudeDeg": -113.3192,
      "depthKm": 12.728,
      "magnitude": 3.2,
      "isLocal": false,
      "nearestTown": null,
      "version": null
    },
    {
      "identifier": "mb90142878",
      "authority": "MB",
      "eventType": "eq",
      "originTimeUtc": 1780198705.57,
      "latitudeDeg": 44.5793333333333,
      "longitudeDeg": -111.184833333333,
      "depthKm": 6.57,
      "magnitude": 0.23,
      "isLocal": false,
      "nearestTown": null,
      "version": null
    },
    {
      "identifier": "mb90142553",
      "authority": "MB",
      "eventType": "eq",
      "originTimeUtc": 1780133177.8500001,
      "latitudeDeg": 44.7198333333333,
      "longitudeDeg": -111.792166666667,
      "depthKm": 12.78,
      "magnitude": 0.81,
      "isLocal": false,
      "nearestTown": null,
      "version": null
    },
    {
      "identifier": "uu80141501",
      "authority": "UU",
      "eventType": "eq",
      "originTimeUtc": 1780461073.13,
      "latitudeDeg": 41.27283333333333,
      "longitudeDeg": -111.721,
      "depthKm": 12.54,
      "magnitude": 1.1400000000000001,
      "isLocal": true,
      "nearestTown": "{'town': 'Huntsville, UT', 'bearing': 'ENE', 'distanceKM': 4.30048153387977}",
      "version": null
    },
    {
      "identifier": "uu80141046",
      "authority": "UU",
      "eventType": "eq",
      "originTimeUtc": 1779727593.1499977,
      "latitudeDeg": 42.098333333333336,
      "longitudeDeg": -112.43133333333333,
      "depthKm": 1.3,
      "magnitude": 1.12,
      "isLocal": true,
      "nearestTown": "{'town': 'Samaria, ID', 'bearing': 'WSW', 'distanceKM': 7.938269127413289}",
      "version": null
    },
    {
      "identifier": "uu80141631",
      "authority": "UU",
      "eventType": "eq",
      "originTimeUtc": 1780719856.709999,
      "latitudeDeg": 41.55466666666667,
      "longitudeDeg": -109.86633333333333,
      "depthKm": -3.45,
      "magnitude": 3.11,
      "isLocal": true,
      "nearestTown": "{'town': 'Little America, WY', 'bearing': 'NNW', 'distanceKM': 1.3419699195680084}",
      "version": null
    },
    {
      "identifier": "uu80141476",
      "authority": "UU",
      "eventType": "eq",
      "originTimeUtc": 1780428644.459999,
      "latitudeDeg": 39.00333333333333,
      "longitudeDeg": -111.9225,
      "depthKm": 14.04,
      "magnitude": 1.54,
      "isLocal": true,
      "nearestTown": "{'town': 'Redmond, UT', 'bearing': 'W', 'distanceKM': 5.245410070070461}",
      "version": null
    },
    {
      "identifier": "uu80141071",
      "authority": "UU",
      "eventType": "eq",
      "originTimeUtc": 1779760024.2199998,
      "latitudeDeg": 44.773666666666664,
      "longitudeDeg": -110.97166666666666,
      "depthKm": 9.59,
      "magnitude": 0.75,
      "isLocal": true,
      "nearestTown": "{'town': 'West Yellowstone, MT', 'bearing': 'NE', 'distanceKM': 16.229415990803723}",
      "version": null
    },
    {
      "identifier": "uu80141331",
      "authority": "UU",
      "eventType": "eq",
      "originTimeUtc": 1780162858.8599968,
      "latitudeDeg": 38.033833333333334,
      "longitudeDeg": -111.68716666666667,
      "depthKm": 9.41,
      "magnitude": 2.12,
      "isLocal": true,
      "nearestTown": "{'town': 'Boulder Town, UT', 'bearing': 'WNW', 'distanceKM': 27.04545988825017}",
      "version": null
    },
    {
      "identifier": "uu80141016",
      "authority": "UU",
      "eventType": "eq",
      "originTimeUtc": 1779659059.3599987,
      "latitudeDeg": 44.181666666666665,
      "longitudeDeg": -110.4355,
      "depthKm": 13.58,
      "magnitude": 1.81,
      "isLocal": true,
      "nearestTown": "{'town': 'West Thumb, WY', 'bearing': 'SSE', 'distanceKM': 28.360930907775455}",
      "version": null
    },
    {
      "identifier": "uu80141131",
      "authority": "UU",
      "eventType": "eq",
      "originTimeUtc": 1779851498.9199982,
      "latitudeDeg": 39.708666666666666,
      "longitudeDeg": -111.94966666666667,
      "depthKm": 11.71,
      "magnitude": 0.72,
      "isLocal": true,
      "nearestTown": "{'town': 'Nephi, UT', 'bearing': 'W', 'distanceKM': 9.699067709635006}",
      "version": null
    },
    {
      "identifier": "uu80141271",
      "authority": "UU",
      "eventType": "eq",
      "originTimeUtc": 1780010179.039999,
      "latitudeDeg": 44.79366666666667,
      "longitudeDeg": -110.8265,
      "depthKm": 4.74,
      "magnitude": 1.19,
      "isLocal": true,
      "nearestTown": "{'town': 'Mammoth, WY', 'bearing': 'SSW', 'distanceKM': 22.541598146067656}",
      "version": null
    },
    {
      "identifier": "uu80141371",
      "authority": "UU",
      "eventType": "eq",
      "originTimeUtc": 1780221831.699997,
      "latitudeDeg": 44.79833333333333,
      "longitudeDeg": -110.83333333333333,
      "depthKm": 4.1,
      "magnitude": 0.21,
      "isLocal": true,
      "nearestTown": "{'town': 'Mammoth, WY', 'bearing': 'SSW', 'distanceKM': 22.31559984009409}",
      "version": null
    },
    {
      "identifier": "mb90143873",
      "authority": "MB",
      "eventType": "eq",
      "originTimeUtc": 1780628743.52,
      "latitudeDeg": 44.8088333333333,
      "longitudeDeg": -111.570833333333,
      "depthKm": 10.64,
      "magnitude": 0.67,
      "isLocal": false,
      "nearestTown": null,
      "version": null
    },
    {
      "identifier": "uu80141546",
      "authority": "UU",
      "eventType": "eq",
      "originTimeUtc": 1780523246.17,
      "latitudeDeg": 44.38633333333333,
      "longitudeDeg": -110.66683333333333,
      "depthKm": 2.31,
      "magnitude": 0.85,
      "isLocal": true,
      "nearestTown": "{'town': 'West Thumb, WY', 'bearing': 'WSW', 'distanceKM': 7.807586078861874}",
      "version": null
    },
    {
      "identifier": "mb90142893",
      "authority": "MB",
      "eventType": "eq",
      "originTimeUtc": 1780219304.98,
      "latitudeDeg": 44.7828333333333,
      "longitudeDeg": -111.369833333333,
      "depthKm": 11.81,
      "magnitude": 0.68,
      "isLocal": false,
      "nearestTown": null,
      "version": null
    },
    {
      "identifier": "uu80141166",
      "authority": "UU",
      "eventType": "eq",
      "originTimeUtc": 1779881693.9199982,
      "latitudeDeg": 39.00483333333333,
      "longitudeDeg": -111.4055,
      "depthKm": -1.4,
      "magnitude": 1.21,
      "isLocal": true,
      "nearestTown": "{'town': 'Emery, UT', 'bearing': 'NW', 'distanceKM': 16.320247501263104}",
      "version": null
    },
    {
      "identifier": "nn00919732",
      "authority": "NN",
      "eventType": "eq",
      "originTimeUtc": 1780581307.3040001,
      "latitudeDeg": 37.2052,
      "longitudeDeg": -114.6894,
      "depthKm": 7.3217,
      "magnitude": 2.09,
      "isLocal": false,
      "nearestTown": null,
      "version": null
    },
    {
      "identifier": "mb90143128",
      "authority": "MB",
      "eventType": "eq",
      "originTimeUtc": 1780294161.92,
      "latitudeDeg": 44.7206666666667,
      "longitudeDeg": -111.169,
      "depthKm": 8.11,
      "magnitude": -0.07,
      "isLocal": false,
      "nearestTown": null,
      "version": null
    },
    {
      "identifier": "uu80141406",
      "authority": "UU",
      "eventType": "eq",
      "originTimeUtc": 1780322260.9799995,
      "latitudeDeg": 37.40133333333333,
      "longitudeDeg": -114.053,
      "depthKm": 12.61,
      "magnitude": 0.9400000000000001,
      "isLocal": true,
      "nearestTown": "{'town': 'Acoma, NV', 'bearing': 'SSE', 'distanceKM': 19.554614727558967}",
      "version": null
    },
    {
      "identifier": "uu80141281",
      "authority": "UU",
      "eventType": "eq",
      "originTimeUtc": 1780050169.6899986,
      "latitudeDeg": 37.304,
      "longitudeDeg": -113.78983333333333,
      "depthKm": 10.13,
      "magnitude": 1.31,
      "isLocal": true,
      "nearestTown": "{'town': 'Gunlock, UT', 'bearing': 'NW', 'distanceKM': 2.64270100266964}",
      "version": null
    },
    {
      "identifier": "mb90142883",
      "authority": "MB",
      "eventType": "eq",
      "originTimeUtc": 1780199066.45,
      "latitudeDeg": 44.838,
      "longitudeDeg": -111.482,
      "depthKm": 12.26,
      "magnitude": 0.44,
      "isLocal": false,
      "nearestTown": null,
      "version": null
    },
    {
      "identifier": "uu80141076",
      "authority": "UU",
      "eventType": "eq",
      "originTimeUtc": 1779782107.79,
      "latitudeDeg": 38.48433333333333,
      "longitudeDeg": -112.90483333333333,
      "depthKm": 2.46,
      "magnitude": 1.28,
      "isLocal": true,
      "nearestTown": "{'town': 'Milford, UT', 'bearing': 'NE', 'distanceKM': 13.405039690440764}",
      "version": null
    },
    {
      "identifier": "uu80141201",
      "authority": "UU",
      "eventType": "eq",
      "originTimeUtc": 1779952962.3199997,
      "latitudeDeg": 38.50833333333333,
      "longitudeDeg": -112.9135,
      "depthKm": 2.04,
      "magnitude": 1.11,
      "isLocal": true,
      "nearestTown": "{'town': 'Milford, UT', 'bearing': 'NE', 'distanceKM': 15.0106943097782}",
      "version": null
    },
    {
      "identifier": "uu80141366",
      "authority": "UU",
      "eventType": "eq",
      "originTimeUtc": 1780214950.6899996,
      "latitudeDeg": 44.793,
      "longitudeDeg": -110.8285,
      "depthKm": 4.64,
      "magnitude": 1.06,
      "isLocal": true,
      "nearestTown": "{'town': 'Mammoth, WY', 'bearing': 'SSW', 'distanceKM': 22.67655909774282}",
      "version": null
    },
    {
      "identifier": "mb90142578",
      "authority": "MB",
      "eventType": "eq",
      "originTimeUtc": 1780184726.79,
      "latitudeDeg": 44.8238333333333,
      "longitudeDeg": -111.5265,
      "depthKm": 11.16,
      "magnitude": 0.6,
      "isLocal": false,
      "nearestTown": null,
      "version": null
    },
    {
      "identifier": "uu80141086",
      "authority": "UU",
      "eventType": "eq",
      "originTimeUtc": 1779799914.75,
      "latitudeDeg": 37.390166666666666,
      "longitudeDeg": -112.5745,
      "depthKm": 14.26,
      "magnitude": 1.52,
      "isLocal": true,
      "nearestTown": "{'town': 'Glendale, UT', 'bearing': 'NNE', 'distanceKM': 8.293181478663394}",
      "version": null
    },
    {
      "identifier": "uu80141411",
      "authority": "UU",
      "eventType": "eq",
      "originTimeUtc": 1780330650.3099995,
      "latitudeDeg": 37.065666666666665,
      "longitudeDeg": -112.86966666666666,
      "depthKm": 8.18,
      "magnitude": 1.68,
      "isLocal": true,
      "nearestTown": "{'town': 'Hildale, UT', 'bearing': 'NE', 'distanceKM': 11.050849878021731}",
      "version": null
    },
    {
      "identifier": "uu80141506",
      "authority": "UU",
      "eventType": "eq",
      "originTimeUtc": 1780461368.04,
      "latitudeDeg": 41.2785,
      "longitudeDeg": -111.72033333333333,
      "depthKm": 12.12,
      "magnitude": 0.75,
      "isLocal": true,
      "nearestTown": "{'town': 'Huntsville, UT', 'bearing': 'ENE', 'distanceKM': 4.586333994107798}",
      "version": null
    },
    {
      "identifier": "nn00919787",
      "authority": "NN",
      "eventType": "eq",
      "originTimeUtc": 1780662324.0,
      "latitudeDeg": 37.1189,
      "longitudeDeg": -114.9108,
      "depthKm": 14.5719,
      "magnitude": 1.52,
      "isLocal": false,
      "nearestTown": null,
      "version": null
    },
    {
      "identifier": "mb90142908",
      "authority": "MB",
      "eventType": "eq",
      "originTimeUtc": 1780221955.8400002,
      "latitudeDeg": 45.6575,
      "longitudeDeg": -111.604333333333,
      "depthKm": 2.39,
      "magnitude": 1.3,
      "isLocal": false,
      "nearestTown": null,
      "version": null
    },
    {
      "identifier": "uu80141091",
      "authority": "UU",
      "eventType": "eq",
      "originTimeUtc": 1779803543.3199997,
      "latitudeDeg": 37.1725,
      "longitudeDeg": -113.40883333333333,
      "depthKm": 2.2,
      "magnitude": 1.43,
      "isLocal": true,
      "nearestTown": "{'town': 'Leeds, UT', 'bearing': 'SSW', 'distanceKM': 8.568689042616105}",
      "version": null
    },
    {
      "identifier": "nn00919392",
      "authority": "NN",
      "eventType": "eq",
      "originTimeUtc": 1780086137.739,
      "latitudeDeg": 35.9682,
      "longitudeDeg": -115.1631,
      "depthKm": 0.0003,
      "magnitude": 2.03,
      "isLocal": false,
      "nearestTown": null,
      "version": null
    },
    {
      "identifier": "uu80141111",
      "authority": "UU",
      "eventType": "eq",
      "originTimeUtc": 1779825267.209999,
      "latitudeDeg": 41.8795,
      "longitudeDeg": -111.51416666666667,
      "depthKm": 6.23,
      "magnitude": 2.0300000000000002,
      "isLocal": true,
      "nearestTown": "{'town': 'Garden City, UT', 'bearing': 'SW', 'distanceKM': 12.484522524747252}",
      "version": null
    },
    {
      "identifier": "uu80141036",
      "authority": "UU",
      "eventType": "eq",
      "originTimeUtc": 1779690649.25,
      "latitudeDeg": 39.36866666666667,
      "longitudeDeg": -112.232,
      "depthKm": 13.69,
      "magnitude": 1.56,
      "isLocal": true,
      "nearestTown": "{'town': 'Oak City, UT', 'bearing': 'E', 'distanceKM': 8.924557882550355}",
      "version": null
    },
    {
      "identifier": "uu80141011",
      "authority": "UU",
      "eventType": "eq",
      "originTimeUtc": 1779650983.790001,
      "latitudeDeg": 41.86183333333334,
      "longitudeDeg": -112.74483333333333,
      "depthKm": -3.46,
      "magnitude": 1.92,
      "isLocal": true,
      "nearestTown": "{'town': 'Snowville, UT', 'bearing': 'SSW', 'distanceKM': 11.888144172984168}",
      "version": null
    },
    {
      "identifier": "uu80141566",
      "authority": "UU",
      "eventType": "eq",
      "originTimeUtc": 1780598179.2299995,
      "latitudeDeg": 40.73266666666667,
      "longitudeDeg": -112.0175,
      "depthKm": 5.98,
      "magnitude": 0.88,
      "isLocal": true,
      "nearestTown": "{'town': 'Magna, UT', 'bearing': 'ENE', 'distanceKM': 8.229515882624296}",
      "version": null
    },
    {
      "identifier": "uu80141266",
      "authority": "UU",
      "eventType": "eq",
      "originTimeUtc": 1780006952.0299988,
      "latitudeDeg": 41.87266666666667,
      "longitudeDeg": -112.7775,
      "depthKm": 0.36,
      "magnitude": 1.01,
      "isLocal": true,
      "nearestTown": "{'town': 'Snowville, UT', 'bearing': 'SSW', 'distanceKM': 11.748390715282921}",
      "version": null
    },
    {
      "identifier": "mb90142403",
      "authority": "MB",
      "eventType": "eq",
      "originTimeUtc": 1780074037.89,
      "latitudeDeg": 44.7621666666667,
      "longitudeDeg": -111.216833333333,
      "depthKm": 9.87,
      "magnitude": 0.29,
      "isLocal": false,
      "nearestTown": null,
      "version": null
    }
  ],
  "stations": []
}
