[
  {
    "event": {
      "evid": "90079838",
      "auth": "mb",
      "magnitude": 2.0,
      "lat": 43.0827,
      "lng": -110.8228,
      "event_time_local": "2025/04/23 10:01:15 MDT",
      "event_time_epoch": 1745424075.36,
      "event_time_utc": "2025/04/23 16:01:15 UTC",
      "depth_mi": 1.4,
      "depth_km": 2.25,
      "version": "n/a",
      "etype": "le"
    }
  },
  {
    "event": {
      "evid": "90079798",
      "auth": "mb",
      "magnitude": 1.5,
      "lat": 44.331,
      "lng": -115.1842,
      "event_time_local": "2025/04/23 05:55:03 MDT",
      "event_time_epoch": 1745409303.06,
      "event_time_utc": "2025/04/23 11:55:03 UTC",
      "depth_mi": 1.7,
      "depth_km": 2.73,
      "version": "n/a",
      "etype": "le"
    }
  },
  {
    "event": {
      "evid": "90079803",
      "auth": "mb",
      "magnitude": 0.5,
      "lat": 45.8258,
      "lng": -112.3967,
      "event_time_local": "2025/04/23 01:34:22 MDT",
      "event_time_epoch": 1745393662.3,
      "event_time_utc": "2025/04/23 07:34:22 UTC",
      "depth_mi": 4.8,
      "depth_km": 7.72,
      "version": "n/a",
      "etype": "le"
    }
  },
  {
    "event": {
      "evid": "90079828",
      "auth": "mb",
      "magnitude": -0.0,
      "lat": 44.6117,
      "lng": -113.0427,
      "event_time_local": "2025/04/22 22:03:56 MDT",
      "event_time_epoch": 1745381036.42,
      "event_time_utc": "2025/04/23 04:03:56 UTC",
      "depth_mi": 3.09,
      "depth_km": 4.97,
      "version": "n/a",
      "etype": "le"
    }
  },
  {
    "event": {
      "evid": "90079823",
      "auth": "mb",
      "magnitude": -0.1,
      "lat": 44.6103,
      "lng": -113.0095,
      "event_time_local": "2025/04/22 22:02:51 MDT",
      "event_time_epoch": 1745380971.26,
      "event_time_utc": "2025/04/23 04:02:51 UTC",
      "depth_mi": 3.09,
      "depth_km": 4.97,
      "version": "n/a",
      "etype": "le"
    }
  },
  {
    "event": {
      "evid": "90079733",
      "auth": "mb",
      "magnitude": 1.3,
      "lat": 45.9277,
      "lng": -111.4837,
      "event_time_local": "2025/04/22 06:31:02 MDT",
      "event_time_epoch": 1745325062.68,
      "event_time_utc": "2025/04/22 12:31:02 UTC",
      "depth_mi": 3.55,
      "depth_km": 5.71,
      "version": "n/a",
      "etype": "le"
    }
  },
  {
    "event": {
      "evid": "90079728",
      "auth": "mb",
      "magnitude": -0.1,
      "lat": 45.8185,
      "lng": -112.4148,
      "event_time_local": "2025/04/22 01:40:34 MDT",
      "event_time_epoch": 1745307634.09,
      "event_time_utc": "2025/04/22 07:40:34 UTC",
      "depth_mi": 5.3,
      "depth_km": 8.54,
      "version": "n/a",
      "etype": "le"
    }
  },
  {
    "event": {
      "evid": "90079723",
      "auth": "mb",
      "magnitude": 0.3,
      "lat": 45.8173,
      "lng": -112.3848,
      "event_time_local": "2025/04/22 01:12:56 MDT",
      "event_time_epoch": 1745305976.29,
      "event_time_utc": "2025/04/22 07:12:56 UTC",
      "depth_mi": 4.61,
      "depth_km": 7.43,
      "version": "n/a",
      "etype": "le"
    }
  },
  {
    "event": {
      "evid": "90079708",
      "auth": "mb",
      "magnitude": 0.6,
      "lat": 45.8255,
      "lng": -112.4012,
      "event_time_local": "2025/04/21 22:30:04 MDT",
      "event_time_epoch": 1745296204.09,
      "event_time_utc": "2025/04/22 04:30:04 UTC",
      "depth_mi": 4.98,
      "depth_km": 8.02,
      "version": "n/a",
      "etype": "le"
    }
  },
  {
    "event": {
      "evid": "90079703",
      "auth": "mb",
      "magnitude": 1.1,
      "lat": 45.6828,
      "lng": -112.146,
      "event_time_local": "2025/04/21 21:28:00 MDT",
      "event_time_epoch": 1745292480.09,
      "event_time_utc": "2025/04/22 03:28:00 UTC",
      "depth_mi": 4.23,
      "depth_km": 6.81,
      "version": "n/a",
      "etype": "le"
    }
  },
  {
    "event": {
      "evid": "90079568",
      "auth": "mb",
      "magnitude": 0.7,
      "lat": 44.5713,
      "lng": -112.4835,
      "event_time_local": "2025/04/21 19:51:35 MDT",
      "event_time_epoch": 1745286695.0,
      "event_time_utc": "2025/04/22 01:51:35 UTC",
      "depth_mi": 4.95,
      "depth_km": 7.97,
      "version": "n/a",
      "etype": "le"
    }
  },
  {
    "event": {
      "evid": "90079698",
      "auth": "mb",
      "magnitude": 0.7,
      "lat": 44.5807,
      "lng": -112.496,
      "event_time_local": "2025/04/21 16:35:37 MDT",
      "event_time_epoch": 1745274937.22,
      "event_time_utc": "2025/04/21 22:35:37 UTC",
      "depth_mi": 3.44,
      "depth_km": 5.54,
      "version": "n/a",
      "etype": "le"
    }
  },
  {
    "event": {
      "evid": "90079688",
      "auth": "mb",
      "magnitude": 0.9,
      "lat": 44.5645,
      "lng": -112.4843,
      "event_time_local": "2025/04/21 16:29:24 MDT",
      "event_time_epoch": 1745274564.07,
      "event_time_utc": "2025/04/21 22:29:24 UTC",
      "depth_mi": 3.89,
      "depth_km": 6.27,
      "version": "n/a",
      "etype": "le"
    }
  },
  {
    "event": {
      "evid": "90079523",
      "auth": "mb",
      "magnitude": 1.4,
      "lat": 44.322,
      "lng": -114.0533,
      "event_time_local": "2025/04/21 14:53:35 MDT",
      "event_time_epoch": 1745268815.73,
      "event_time_utc": "2025/04/21 20:53:35 UTC",
      "depth_mi": 2.89,
      "depth_km": 4.65,
      "version": "n/a",
      "etype": "le"
    }
  },
  {
    "event": {
      "evid": "90079518",
      "auth": "mb",
      "magnitude": 1.4,
      "lat": 44.3065,
      "lng": -114.0523,
      "event_time_local": "2025/04/21 14:43:47 MDT",
      "event_time_epoch": 1745268227.45,
      "event_time_utc": "2025/04/21 20:43:47 UTC",
      "depth_mi": 2.35,
      "depth_km": 3.78,
      "version": "n/a",
      "etype": "le"
    }
  },
  {
    "event": {
      "evid": "00896634",
      "auth": "nn",
      "magnitude": 1.3,
      "lat": 36.5213,
      "lng": -114.0072,
      "event_time_local": "2025/04/21 13:07:30 MDT",
      "event_time_epoch": 1745262450.713,
      "event_time_utc": "2025/04/21 19:07:30 UTC",
      "depth_mi": 3.42,
      "depth_km": 5.5,
      "version": "n/a",
      "etype": "le"
    }
  },
  {
    "event": {
      "evid": "90079633",
      "auth": "mb",
      "magnitude": 2.2,
      "lat": 44.1993,
      "lng": -115.086,
      "event_time_local": "2025/04/21 09:00:00 MDT",
      "event_time_epoch": 1745247600.68,
      "event_time_utc": "2025/04/21 15:00:00 UTC",
      "depth_mi": 4.65,
      "depth_km": 7.49,
      "version": "n/a",
      "etype": "le"
    }
  },
  {
    "event": {
      "evid": "00896619",
      "auth": "nn",
      "magnitude": 1.5,
      "lat": 37.3125,
      "lng": -114.6466,
      "event_time_local": "2025/04/21 07:10:06 MDT",
      "event_time_epoch": 1745241006.97,
      "event_time_utc": "2025/04/21 13:10:06 UTC",
      "depth_mi": 5.03,
      "depth_km": 8.1,
      "version": "n/a",
      "etype": "le"
    }
  },
  {
    "event": {
      "evid": "90079863",
      "auth": "mb",
      "magnitude": -0.4,
      "lat": 45.4038,
      "lng": -111.7558,
      "event_time_local": "2025/04/21 04:39:33 MDT",
      "event_time_epoch": 1745231973.35,
      "event_time_utc": "2025/04/21 10:39:33 UTC",
      "depth_mi": 4.31,
      "depth_km": 6.94,
      "version": "n/a",
      "etype": "le"
    }
  },
  {
    "event": {
      "evid": "90079848",
      "auth": "mb",
      "magnitude": 0.0,
      "lat": 45.3057,
      "lng": -111.688,
      "event_time_local": "2025/04/21 04:21:00 MDT",
      "event_time_epoch": 1745230860.1,
      "event_time_utc": "2025/04/21 10:21:00 UTC",
      "depth_mi": 3.07,
      "depth_km": 4.94,
      "version": "n/a",
      "etype": "le"
    }
  },
  {
    "event": {
      "evid": "90079813",
      "auth": "mb",
      "magnitude": 0.2,
      "lat": 44.7792,
      "lng": -112.7917,
      "event_time_local": "2025/04/21 04:07:03 MDT",
      "event_time_epoch": 1745230023.04,
      "event_time_utc": "2025/04/21 10:07:03 UTC",
      "depth_mi": 6.48,
      "depth_km": 10.43,
      "version": "n/a",
      "etype": "le"
    }
  },
  {
    "event": {
      "evid": "90079448",
      "auth": "mb",
      "magnitude": 1.4,
      "lat": 44.9853,
      "lng": -111.9187,
      "event_time_local": "2025/04/21 01:50:13 MDT",
      "event_time_epoch": 1745221813.59,
      "event_time_utc": "2025/04/21 07:50:13 UTC",
      "depth_mi": 0.79,
      "depth_km": 1.27,
      "version": "n/a",
      "etype": "le"
    }
  },
  {
    "event": {
      "evid": "90079808",
      "auth": "mb",
      "magnitude": 1.0,
      "lat": 44.1322,
      "lng": -113.967,
      "event_time_local": "2025/04/20 23:04:34 MDT",
      "event_time_epoch": 1745211874.99,
      "event_time_utc": "2025/04/21 05:04:34 UTC",
      "depth_mi": 3.08,
      "depth_km": 4.96,
      "version": "n/a",
      "etype": "le"
    }
  },
  {
    "event": {
      "evid": "90079628",
      "auth": "mb",
      "magnitude": 0.4,
      "lat": 44.5848,
      "lng": -112.4862,
      "event_time_local": "2025/04/20 21:18:49 MDT",
      "event_time_epoch": 1745205529.13,
      "event_time_utc": "2025/04/21 03:18:49 UTC",
      "depth_mi": 5.75,
      "depth_km": 9.25,
      "version": "n/a",
      "etype": "le"
    }
  },
  {
    "event": {
      "evid": "90079623",
      "auth": "mb",
      "magnitude": 1.2,
      "lat": 44.0455,
      "lng": -113.8373,
      "event_time_local": "2025/04/20 16:46:55 MDT",
      "event_time_epoch": 1745189215.49,
      "event_time_utc": "2025/04/20 22:46:55 UTC",
      "depth_mi": 3.11,
      "depth_km": 5.0,
      "version": "n/a",
      "etype": "le"
    }
  },
  {
    "event": {
      "evid": "90079618",
      "auth": "mb",
      "magnitude": 0.8,
      "lat": 44.581,
      "lng": -112.4882,
      "event_time_local": "2025/04/20 16:46:00 MDT",
      "event_time_epoch": 1745189160.08,
      "event_time_utc": "2025/04/20 22:46:00 UTC",
      "depth_mi": 5.45,
      "depth_km": 8.77,
      "version": "n/a",
      "etype": "le"
    }
  },
  {
    "event": {
      "evid": "90079418",
      "auth": "mb",
      "magnitude": 2.2,
      "lat": 43.4975,
      "lng": -110.5455,
      "event_time_local": "2025/04/20 16:40:45 MDT",
      "event_time_epoch": 1745188845.36,
      "event_time_utc": "2025/04/20 22:40:45 UTC",
      "depth_mi": 3.37,
      "depth_km": 5.42,
      "version": "n/a",
      "etype": "le"
    }
  },
  {
    "event": {
      "evid": "6000q7fp",
      "auth": "us",
      "magnitude": 2.9,
      "lat": 43.4726,
      "lng": -110.5874,
      "event_time_local": "2025/04/20 15:14:46 MDT",
      "event_time_epoch": 1745183686.387,
      "event_time_utc": "2025/04/20 21:14:46 UTC",
      "depth_mi": 3.87,
      "depth_km": 6.22,
      "version": "n/a",
      "etype": "le"
    }
  },
  {
    "event": {
      "evid": "90079613",
      "auth": "mb",
      "magnitude": 1.0,
      "lat": 44.5803,
      "lng": -112.4835,
      "event_time_local": "2025/04/20 15:14:08 MDT",
      "event_time_epoch": 1745183648.17,
      "event_time_utc": "2025/04/20 21:14:08 UTC",
      "depth_mi": 5.97,
      "depth_km": 9.61,
      "version": "n/a",
      "etype": "le"
    }
  },
  {
    "event": {
      "evid": "90079398",
      "auth": "mb",
      "magnitude": 1.8,
      "lat": 44.5693,
      "lng": -112.4847,
      "event_time_local": "2025/04/20 15:08:21 MDT",
      "event_time_epoch": 1745183301.31,
      "event_time_utc": "2025/04/20 21:08:21 UTC",
      "depth_mi": 4.97,
      "depth_km": 8.0,
      "version": "n/a",
      "etype": "le"
    }
  },
  {
    "event": {
      "evid": "90079608",
      "auth": "mb",
      "magnitude": 0.6,
      "lat": 44.5838,
      "lng": -112.4878,
      "event_time_local": "2025/04/20 07:38:24 MDT",
      "event_time_epoch": 1745156304.03,
      "event_time_utc": "2025/04/20 13:38:24 UTC",
      "depth_mi": 6.03,
      "depth_km": 9.71,
      "version": "n/a",
      "etype": "le"
    }
  },
  {
    "event": {
      "evid": "90079603",
      "auth": "mb",
      "magnitude": 1.0,
      "lat": 44.5617,
      "lng": -112.0993,
      "event_time_local": "2025/04/20 06:25:36 MDT",
      "event_time_epoch": 1745151936.58,
      "event_time_utc": "2025/04/20 12:25:36 UTC",
      "depth_mi": 3.09,
      "depth_km": 4.98,
      "version": "n/a",
      "etype": "le"
    }
  },
  {
    "event": {
      "evid": "90079378",
      "auth": "mb",
      "magnitude": 1.7,
      "lat": 44.5743,
      "lng": -112.4887,
      "event_time_local": "2025/04/20 04:09:43 MDT",
      "event_time_epoch": 1745143783.03,
      "event_time_utc": "2025/04/20 10:09:43 UTC",
      "depth_mi": 5.04,
      "depth_km": 8.12,
      "version": "n/a",
      "etype": "le"
    }
  },
  {
    "event": {
      "evid": "90079598",
      "auth": "mb",
      "magnitude": 0.8,
      "lat": 44.5803,
      "lng": -112.4838,
      "event_time_local": "2025/04/20 03:53:09 MDT",
      "event_time_epoch": 1745142789.08,
      "event_time_utc": "2025/04/20 09:53:09 UTC",
      "depth_mi": 6.33,
      "depth_km": 10.19,
      "version": "n/a",
      "etype": "le"
    }
  },
  {
    "event": {
      "evid": "90079593",
      "auth": "mb",
      "magnitude": 0.8,
      "lat": 44.5743,
      "lng": -112.4932,
      "event_time_local": "2025/04/20 03:50:20 MDT",
      "event_time_epoch": 1745142620.4,
      "event_time_utc": "2025/04/20 09:50:20 UTC",
      "depth_mi": 4.63,
      "depth_km": 7.46,
      "version": "n/a",
      "etype": "le"
    }
  },
  {
    "event": {
      "evid": "6000q7d3",
      "auth": "us",
      "magnitude": 2.6,
      "lat": 44.5848,
      "lng": -112.4943,
      "event_time_local": "2025/04/20 02:59:07 MDT",
      "event_time_epoch": 1745139547.102,
      "event_time_utc": "2025/04/20 08:59:07 UTC",
      "depth_mi": 8.65,
      "depth_km": 13.93,
      "version": "n/a",
      "etype": "le"
    }
  },
  {
    "event": {
      "evid": "90079588",
      "auth": "mb",
      "magnitude": 0.8,
      "lat": 44.5777,
      "lng": -112.484,
      "event_time_local": "2025/04/20 02:38:53 MDT",
      "event_time_epoch": 1745138333.37,
      "event_time_utc": "2025/04/20 08:38:53 UTC",
      "depth_mi": 5.73,
      "depth_km": 9.23,
      "version": "n/a",
      "etype": "le"
    }
  },
  {
    "event": {
      "evid": "90079583",
      "auth": "mb",
      "magnitude": 0.5,
      "lat": 44.5722,
      "lng": -112.485,
      "event_time_local": "2025/04/20 02:22:33 MDT",
      "event_time_epoch": 1745137353.0,
      "event_time_utc": "2025/04/20 08:22:33 UTC",
      "depth_mi": 5.8,
      "depth_km": 9.34,
      "version": "n/a",
      "etype": "le"
    }
  },
  {
    "event": {
      "evid": "90079533",
      "auth": "mb",
      "magnitude": 0.7,
      "lat": 44.5698,
      "lng": -112.4818,
      "event_time_local": "2025/04/20 02:17:18 MDT",
      "event_time_epoch": 1745137038.23,
      "event_time_utc": "2025/04/20 08:17:18 UTC",
      "depth_mi": 5.88,
      "depth_km": 9.46,
      "version": "n/a",
      "etype": "le"
    }
  },
  {
    "event": {
      "evid": "90079498",
      "auth": "mb",
      "magnitude": 0.8,
      "lat": 44.5697,
      "lng": -112.4797,
      "event_time_local": "2025/04/20 02:16:39 MDT",
      "event_time_epoch": 1745136999.2,
      "event_time_utc": "2025/04/20 08:16:39 UTC",
      "depth_mi": 5.43,
      "depth_km": 8.74,
      "version": "n/a",
      "etype": "le"
    }
  },
  {
    "event": {
      "evid": "90079363",
      "auth": "mb",
      "magnitude": 1.0,
      "lat": 44.571,
      "lng": -112.4905,
      "event_time_local": "2025/04/20 02:14:55 MDT",
      "event_time_epoch": 1745136895.28,
      "event_time_utc": "2025/04/20 08:14:55 UTC",
      "depth_mi": 4.84,
      "depth_km": 7.8,
      "version": "n/a",
      "etype": "le"
    }
  },
  {
    "event": {
      "evid": "90079348",
      "auth": "mb",
      "magnitude": 1.2,
      "lat": 44.5773,
      "lng": -112.485,
      "event_time_local": "2025/04/20 01:59:46 MDT",
      "event_time_epoch": 1745135986.61,
      "event_time_utc": "2025/04/20 07:59:46 UTC",
      "depth_mi": 5.09,
      "depth_km": 8.19,
      "version": "n/a",
      "etype": "le"
    }
  },
  {
    "event": {
      "evid": "90079483",
      "auth": "mb",
      "magnitude": 0.8,
      "lat": 44.7177,
      "lng": -112.444,
      "event_time_local": "2025/04/19 10:08:23 MDT",
      "event_time_epoch": 1745078903.08,
      "event_time_utc": "2025/04/19 16:08:23 UTC",
      "depth_mi": 0.31,
      "depth_km": 0.5,
      "version": "n/a",
      "etype": "le"
    }
  },
  {
    "event": {
      "evid": "90079473",
      "auth": "mb",
      "magnitude": 0.9,
      "lat": 44.7175,
      "lng": -112.4273,
      "event_time_local": "2025/04/19 10:04:20 MDT",
      "event_time_epoch": 1745078660.45,
      "event_time_utc": "2025/04/19 16:04:20 UTC",
      "depth_mi": 3.02,
      "depth_km": 4.87,
      "version": "n/a",
      "etype": "le"
    }
  },
  {
    "event": {
      "evid": "90079318",
      "auth": "mb",
      "magnitude": 0.9,
      "lat": 44.5678,
      "lng": -112.4902,
      "event_time_local": "2025/04/19 02:19:29 MDT",
      "event_time_epoch": 1745050769.82,
      "event_time_utc": "2025/04/19 08:19:29 UTC",
      "depth_mi": 4.67,
      "depth_km": 7.52,
      "version": "n/a",
      "etype": "le"
    }
  },
  {
    "event": {
      "evid": "90079313",
      "auth": "mb",
      "magnitude": 1.2,
      "lat": 44.5652,
      "lng": -112.492,
      "event_time_local": "2025/04/19 02:12:55 MDT",
      "event_time_epoch": 1745050375.43,
      "event_time_utc": "2025/04/19 08:12:55 UTC",
      "depth_mi": 3.71,
      "depth_km": 5.98,
      "version": "n/a",
      "etype": "le"
    }
  },
  {
    "event": {
      "evid": "90079238",
      "auth": "mb",
      "magnitude": 0.9,
      "lat": 43.4958,
      "lng": -110.5575,
      "event_time_local": "2025/04/18 07:46:03 MDT",
      "event_time_epoch": 1744983963.04,
      "event_time_utc": "2025/04/18 13:46:03 UTC",
      "depth_mi": 3.22,
      "depth_km": 5.18,
      "version": "n/a",
      "etype": "le"
    }
  },
  {
    "event": {
      "evid": "6000q70q",
      "auth": "us",
      "magnitude": 2.9,
      "lat": 43.4728,
      "lng": -110.5953,
      "event_time_local": "2025/04/18 07:25:55 MDT",
      "event_time_epoch": 1744982755.996,
      "event_time_utc": "2025/04/18 13:25:55 UTC",
      "depth_mi": 5.05,
      "depth_km": 8.13,
      "version": "n/a",
      "etype": "le"
    }
  },
  {
    "event": {
      "evid": "90079228",
      "auth": "mb",
      "magnitude": 0.2,
      "lat": 43.5042,
      "lng": -110.5658,
      "event_time_local": "2025/04/18 07:14:50 MDT",
      "event_time_epoch": 1744982090.3,
      "event_time_utc": "2025/04/18 13:14:50 UTC",
      "depth_mi": 3.85,
      "depth_km": 6.2,
      "version": "n/a",
      "etype": "le"
    }
  },
  {
    "event": {
      "evid": "90079258",
      "auth": "mb",
      "magnitude": 0.7,
      "lat": 44.7398,
      "lng": -112.444,
      "event_time_local": "2025/04/18 05:53:36 MDT",
      "event_time_epoch": 1744977216.74,
      "event_time_utc": "2025/04/18 11:53:36 UTC",
      "depth_mi": 2.5,
      "depth_km": 4.03,
      "version": "n/a",
      "etype": "le"
    }
  },
  {
    "event": {
      "evid": "90079253",
      "auth": "mb",
      "magnitude": 0.5,
      "lat": 44.7358,
      "lng": -112.4402,
      "event_time_local": "2025/04/18 05:10:09 MDT",
      "event_time_epoch": 1744974609.47,
      "event_time_utc": "2025/04/18 11:10:09 UTC",
      "depth_mi": 4.89,
      "depth_km": 7.87,
      "version": "n/a",
      "etype": "le"
    }
  },
  {
    "event": {
      "evid": "6000q6yt",
      "auth": "us",
      "magnitude": 3.9,
      "lat": 43.4703,
      "lng": -110.5542,
      "event_time_local": "2025/04/17 23:07:14 MDT",
      "event_time_epoch": 1744952834.58,
      "event_time_utc": "2025/04/18 05:07:14 UTC",
      "depth_mi": 2.38,
      "depth_km": 3.84,
      "version": "n/a",
      "etype": "le"
    }
  },
  {
    "event": {
      "evid": "90079173",
      "auth": "mb",
      "magnitude": 0.9,
      "lat": 44.3528,
      "lng": -112.722,
      "event_time_local": "2025/04/17 18:53:20 MDT",
      "event_time_epoch": 1744937600.8,
      "event_time_utc": "2025/04/18 00:53:20 UTC",
      "depth_mi": 2.2,
      "depth_km": 3.55,
      "version": "n/a",
      "etype": "le"
    }
  },
  {
    "event": {
      "evid": "90079093",
      "auth": "mb",
      "magnitude": 1.1,
      "lat": 44.739,
      "lng": -112.4282,
      "event_time_local": "2025/04/17 06:46:40 MDT",
      "event_time_epoch": 1744894000.58,
      "event_time_utc": "2025/04/17 12:46:40 UTC",
      "depth_mi": 4.0,
      "depth_km": 6.44,
      "version": "n/a",
      "etype": "le"
    }
  },
  {
    "event": {
      "evid": "90079053",
      "auth": "mb",
      "magnitude": 1.4,
      "lat": 44.5805,
      "lng": -112.5308,
      "event_time_local": "2025/04/16 22:27:16 MDT",
      "event_time_epoch": 1744864036.43,
      "event_time_utc": "2025/04/17 04:27:16 UTC",
      "depth_mi": 9.88,
      "depth_km": 15.91,
      "version": "n/a",
      "etype": "le"
    }
  },
  {
    "event": {
      "evid": "90079083",
      "auth": "mb",
      "magnitude": 0.6,
      "lat": 45.3378,
      "lng": -112.5965,
      "event_time_local": "2025/04/16 21:15:01 MDT",
      "event_time_epoch": 1744859701.12,
      "event_time_utc": "2025/04/17 03:15:01 UTC",
      "depth_mi": 4.75,
      "depth_km": 7.64,
      "version": "n/a",
      "etype": "le"
    }
  },
  {
    "event": {
      "evid": "90079028",
      "auth": "mb",
      "magnitude": 2.4,
      "lat": 45.7477,
      "lng": -114.6463,
      "event_time_local": "2025/04/16 17:47:58 MDT",
      "event_time_epoch": 1744847278.72,
      "event_time_utc": "2025/04/16 23:47:58 UTC",
      "depth_mi": 13.74,
      "depth_km": 22.12,
      "version": "n/a",
      "etype": "le"
    }
  },
  {
    "event": {
      "evid": "6000q6li",
      "auth": "us",
      "magnitude": 2.4,
      "lat": 44.3043,
      "lng": -113.2134,
      "event_time_local": "2025/04/16 14:43:02 MDT",
      "event_time_epoch": 1744836182.312,
      "event_time_utc": "2025/04/16 20:43:02 UTC",
      "depth_mi": 5.08,
      "depth_km": 8.18,
      "version": "n/a",
      "etype": "le"
    }
  },
  {
    "event": {
      "evid": "90079078",
      "auth": "mb",
      "magnitude": 2.0,
      "lat": 43.6023,
      "lng": -110.4622,
      "event_time_local": "2025/04/16 12:11:11 MDT",
      "event_time_epoch": 1744827071.64,
      "event_time_utc": "2025/04/16 18:11:11 UTC",
      "depth_mi": 2.63,
      "depth_km": 4.23,
      "version": "n/a",
      "etype": "le"
    }
  },
  {
    "event": {
      "evid": "90078908",
      "auth": "mb",
      "magnitude": 1.8,
      "lat": 44.3427,
      "lng": -115.1767,
      "event_time_local": "2025/04/16 09:00:49 MDT",
      "event_time_epoch": 1744815649.22,
      "event_time_utc": "2025/04/16 15:00:49 UTC",
      "depth_mi": 6.73,
      "depth_km": 10.84,
      "version": "n/a",
      "etype": "le"
    }
  },
  {
    "event": {
      "evid": "90078898",
      "auth": "mb",
      "magnitude": 0.0,
      "lat": 44.6297,
      "lng": -112.5785,
      "event_time_local": "2025/04/16 04:19:03 MDT",
      "event_time_epoch": 1744798743.78,
      "event_time_utc": "2025/04/16 10:19:03 UTC",
      "depth_mi": 2.14,
      "depth_km": 3.44,
      "version": "n/a",
      "etype": "le"
    }
  },
  {
    "event": {
      "evid": "90078918",
      "auth": "mb",
      "magnitude": 0.1,
      "lat": 45.1003,
      "lng": -111.9378,
      "event_time_local": "2025/04/16 03:15:47 MDT",
      "event_time_epoch": 1744794947.04,
      "event_time_utc": "2025/04/16 09:15:47 UTC",
      "depth_mi": 1.65,
      "depth_km": 2.66,
      "version": "n/a",
      "etype": "le"
    }
  },
  {
    "event": {
      "evid": "90078913",
      "auth": "mb",
      "magnitude": 0.0,
      "lat": 44.797,
      "lng": -111.4513,
      "event_time_local": "2025/04/16 01:32:33 MDT",
      "event_time_epoch": 1744788753.23,
      "event_time_utc": "2025/04/16 07:32:33 UTC",
      "depth_mi": 5.96,
      "depth_km": 9.59,
      "version": "n/a",
      "etype": "le"
    }
  },
  {
    "event": {
      "evid": "90078868",
      "auth": "mb",
      "magnitude": 0.3,
      "lat": 44.8395,
      "lng": -111.449,
      "event_time_local": "2025/04/15 22:27:56 MDT",
      "event_time_epoch": 1744777676.48,
      "event_time_utc": "2025/04/16 04:27:56 UTC",
      "depth_mi": 4.98,
      "depth_km": 8.01,
      "version": "n/a",
      "etype": "le"
    }
  },
  {
    "event": {
      "evid": "90078893",
      "auth": "mb",
      "magnitude": 1.5,
      "lat": 44.3522,
      "lng": -115.1835,
      "event_time_local": "2025/04/15 20:08:28 MDT",
      "event_time_epoch": 1744769308.5,
      "event_time_utc": "2025/04/16 02:08:28 UTC",
      "depth_mi": 3.01,
      "depth_km": 4.84,
      "version": "n/a",
      "etype": "le"
    }
  },
  {
    "event": {
      "evid": "90078788",
      "auth": "mb",
      "magnitude": 0.9,
      "lat": 44.5777,
      "lng": -114.0798,
      "event_time_local": "2025/04/15 07:23:52 MDT",
      "event_time_epoch": 1744723432.67,
      "event_time_utc": "2025/04/15 13:23:52 UTC",
      "depth_mi": 0.63,
      "depth_km": 1.01,
      "version": "n/a",
      "etype": "le"
    }
  },
  {
    "event": {
      "evid": "90078808",
      "auth": "mb",
      "magnitude": -0.0,
      "lat": 44.8215,
      "lng": -111.5023,
      "event_time_local": "2025/04/15 04:13:15 MDT",
      "event_time_epoch": 1744711995.27,
      "event_time_utc": "2025/04/15 10:13:15 UTC",
      "depth_mi": 5.93,
      "depth_km": 9.54,
      "version": "n/a",
      "etype": "le"
    }
  },
  {
    "event": {
      "evid": "90078803",
      "auth": "mb",
      "magnitude": -0.3,
      "lat": 44.8195,
      "lng": -111.5157,
      "event_time_local": "2025/04/15 04:01:48 MDT",
      "event_time_epoch": 1744711308.0,
      "event_time_utc": "2025/04/15 10:01:48 UTC",
      "depth_mi": 3.66,
      "depth_km": 5.89,
      "version": "n/a",
      "etype": "le"
    }
  },
  {
    "event": {
      "evid": "90078783",
      "auth": "mb",
      "magnitude": 1.2,
      "lat": 44.513,
      "lng": -115.2213,
      "event_time_local": "2025/04/15 02:15:02 MDT",
      "event_time_epoch": 1744704902.12,
      "event_time_utc": "2025/04/15 08:15:02 UTC",
      "depth_mi": 5.19,
      "depth_km": 8.36,
      "version": "n/a",
      "etype": "le"
    }
  },
  {
    "event": {
      "evid": "90078818",
      "auth": "mb",
      "magnitude": -0.4,
      "lat": 44.8043,
      "lng": -111.4878,
      "event_time_local": "2025/04/15 01:26:39 MDT",
      "event_time_epoch": 1744701999.92,
      "event_time_utc": "2025/04/15 07:26:39 UTC",
      "depth_mi": 5.1,
      "depth_km": 8.21,
      "version": "n/a",
      "etype": "le"
    }
  },
  {
    "event": {
      "evid": "90078813",
      "auth": "mb",
      "magnitude": -0.2,
      "lat": 44.7727,
      "lng": -111.6182,
      "event_time_local": "2025/04/14 22:15:49 MDT",
      "event_time_epoch": 1744690549.18,
      "event_time_utc": "2025/04/15 04:15:49 UTC",
      "depth_mi": 5.57,
      "depth_km": 8.97,
      "version": "n/a",
      "etype": "le"
    }
  },
  {
    "event": {
      "evid": "90078798",
      "auth": "mb",
      "magnitude": -0.0,
      "lat": 44.8365,
      "lng": -111.4478,
      "event_time_local": "2025/04/14 20:37:26 MDT",
      "event_time_epoch": 1744684646.33,
      "event_time_utc": "2025/04/15 02:37:26 UTC",
      "depth_mi": 4.93,
      "depth_km": 7.93,
      "version": "n/a",
      "etype": "le"
    }
  },
  {
    "event": {
      "evid": "90078678",
      "auth": "mb",
      "magnitude": 0.8,
      "lat": 45.3205,
      "lng": -112.5905,
      "event_time_local": "2025/04/14 13:23:02 MDT",
      "event_time_epoch": 1744658582.21,
      "event_time_utc": "2025/04/14 19:23:02 UTC",
      "depth_mi": 5.02,
      "depth_km": 8.08,
      "version": "n/a",
      "etype": "le"
    }
  },
  {
    "event": {
      "evid": "90078668",
      "auth": "mb",
      "magnitude": 2.2,
      "lat": 44.516,
      "lng": -115.213,
      "event_time_local": "2025/04/14 13:01:21 MDT",
      "event_time_epoch": 1744657281.16,
      "event_time_utc": "2025/04/14 19:01:21 UTC",
      "depth_mi": 6.17,
      "depth_km": 9.93,
      "version": "n/a",
      "etype": "le"
    }
  },
  {
    "event": {
      "evid": "90078663",
      "auth": "mb",
      "magnitude": 1.5,
      "lat": 44.5153,
      "lng": -115.2157,
      "event_time_local": "2025/04/14 12:32:10 MDT",
      "event_time_epoch": 1744655530.22,
      "event_time_utc": "2025/04/14 18:32:10 UTC",
      "depth_mi": 5.98,
      "depth_km": 9.63,
      "version": "n/a",
      "etype": "le"
    }
  },
  {
    "event": {
      "evid": "90078553",
      "auth": "mb",
      "magnitude": 0.9,
      "lat": 44.8383,
      "lng": -111.4512,
      "event_time_local": "2025/04/14 08:01:17 MDT",
      "event_time_epoch": 1744639277.45,
      "event_time_utc": "2025/04/14 14:01:17 UTC",
      "depth_mi": 4.33,
      "depth_km": 6.97,
      "version": "n/a",
      "etype": "le"
    }
  },
  {
    "event": {
      "evid": "90078578",
      "auth": "mb",
      "magnitude": 0.7,
      "lat": 44.6162,
      "lng": -112.0867,
      "event_time_local": "2025/04/14 07:06:23 MDT",
      "event_time_epoch": 1744635983.78,
      "event_time_utc": "2025/04/14 13:06:23 UTC",
      "depth_mi": 4.55,
      "depth_km": 7.33,
      "version": "n/a",
      "etype": "le"
    }
  },
  {
    "event": {
      "evid": "90078708",
      "auth": "mb",
      "magnitude": -0.2,
      "lat": 44.7457,
      "lng": -111.5925,
      "event_time_local": "2025/04/14 06:50:55 MDT",
      "event_time_epoch": 1744635055.77,
      "event_time_utc": "2025/04/14 12:50:55 UTC",
      "depth_mi": 6.85,
      "depth_km": 11.03,
      "version": "n/a",
      "etype": "le"
    }
  },
  {
    "event": {
      "evid": "90078573",
      "auth": "mb",
      "magnitude": 0.9,
      "lat": 45.3213,
      "lng": -112.5965,
      "event_time_local": "2025/04/14 05:55:06 MDT",
      "event_time_epoch": 1744631706.56,
      "event_time_utc": "2025/04/14 11:55:06 UTC",
      "depth_mi": 5.24,
      "depth_km": 8.43,
      "version": "n/a",
      "etype": "le"
    }
  },
  {
    "event": {
      "evid": "90078728",
      "auth": "mb",
      "magnitude": -0.4,
      "lat": 44.8297,
      "lng": -111.4657,
      "event_time_local": "2025/04/13 23:13:12 MDT",
      "event_time_epoch": 1744607592.29,
      "event_time_utc": "2025/04/14 05:13:12 UTC",
      "depth_mi": 4.17,
      "depth_km": 6.72,
      "version": "n/a",
      "etype": "le"
    }
  },
  {
    "event": {
      "evid": "90078518",
      "auth": "mb",
      "magnitude": 1.6,
      "lat": 44.313,
      "lng": -115.172,
      "event_time_local": "2025/04/13 18:51:53 MDT",
      "event_time_epoch": 1744591913.45,
      "event_time_utc": "2025/04/14 00:51:53 UTC",
      "depth_mi": 2.76,
      "depth_km": 4.45,
      "version": "n/a",
      "etype": "le"
    }
  },
  {
    "event": {
      "evid": "90078563",
      "auth": "mb",
      "magnitude": 0.2,
      "lat": 45.3535,
      "lng": -112.5515,
      "event_time_local": "2025/04/13 13:39:06 MDT",
      "event_time_epoch": 1744573146.64,
      "event_time_utc": "2025/04/13 19:39:06 UTC",
      "depth_mi": 5.76,
      "depth_km": 9.28,
      "version": "n/a",
      "etype": "le"
    }
  },
  {
    "event": {
      "evid": "90078558",
      "auth": "mb",
      "magnitude": 1.5,
      "lat": 44.6528,
      "lng": -114.3745,
      "event_time_local": "2025/04/13 05:57:20 MDT",
      "event_time_epoch": 1744545440.21,
      "event_time_utc": "2025/04/13 11:57:20 UTC",
      "depth_mi": 3.93,
      "depth_km": 6.33,
      "version": "n/a",
      "etype": "le"
    }
  },
  {
    "event": {
      "evid": "90078433",
      "auth": "mb",
      "magnitude": 0.1,
      "lat": 45.1403,
      "lng": -111.7453,
      "event_time_local": "2025/04/13 02:45:30 MDT",
      "event_time_epoch": 1744533930.97,
      "event_time_utc": "2025/04/13 08:45:30 UTC",
      "depth_mi": 4.32,
      "depth_km": 6.95,
      "version": "n/a",
      "etype": "le"
    }
  },
  {
    "event": {
      "evid": "90078423",
      "auth": "mb",
      "magnitude": 0.6,
      "lat": 44.9113,
      "lng": -111.4872,
      "event_time_local": "2025/04/13 01:46:06 MDT",
      "event_time_epoch": 1744530366.2,
      "event_time_utc": "2025/04/13 07:46:06 UTC",
      "depth_mi": 6.15,
      "depth_km": 9.9,
      "version": "n/a",
      "etype": "le"
    }
  },
  {
    "event": {
      "evid": "90078723",
      "auth": "mb",
      "magnitude": -0.1,
      "lat": 44.8238,
      "lng": -111.427,
      "event_time_local": "2025/04/13 01:40:31 MDT",
      "event_time_epoch": 1744530031.72,
      "event_time_utc": "2025/04/13 07:40:31 UTC",
      "depth_mi": 5.29,
      "depth_km": 8.51,
      "version": "n/a",
      "etype": "le"
    }
  },
  {
    "event": {
      "evid": "00896143",
      "auth": "nn",
      "magnitude": 1.0,
      "lat": 36.5159,
      "lng": -113.9979,
      "event_time_local": "2025/04/12 23:20:48 MDT",
      "event_time_epoch": 1744521648.739,
      "event_time_utc": "2025/04/13 05:20:48 UTC",
      "depth_mi": 6.4,
      "depth_km": 10.3,
      "version": "n/a",
      "etype": "le"
    }
  },
  {
    "event": {
      "evid": "90078718",
      "auth": "mb",
      "magnitude": -0.2,
      "lat": 44.8352,
      "lng": -111.492,
      "event_time_local": "2025/04/12 06:23:46 MDT",
      "event_time_epoch": 1744460626.59,
      "event_time_utc": "2025/04/12 12:23:46 UTC",
      "depth_mi": 8.01,
      "depth_km": 12.9,
      "version": "n/a",
      "etype": "le"
    }
  },
  {
    "event": {
      "evid": "00896120",
      "auth": "nn",
      "magnitude": 1.1,
      "lat": 36.9973,
      "lng": -115.1004,
      "event_time_local": "2025/04/12 03:03:04 MDT",
      "event_time_epoch": 1744448584.676,
      "event_time_utc": "2025/04/12 09:03:04 UTC",
      "depth_mi": 0.0,
      "depth_km": 0.0,
      "version": "n/a",
      "etype": "le"
    }
  },
  {
    "event": {
      "evid": "90078133",
      "auth": "mb",
      "magnitude": 0.6,
      "lat": 44.8797,
      "lng": -111.5108,
      "event_time_local": "2025/04/11 23:59:33 MDT",
      "event_time_epoch": 1744437573.48,
      "event_time_utc": "2025/04/12 05:59:33 UTC",
      "depth_mi": 6.5,
      "depth_km": 10.47,
      "version": "n/a",
      "etype": "le"
    }
  },
  {
    "event": {
      "evid": "90078698",
      "auth": "mb",
      "magnitude": -0.2,
      "lat": 44.846,
      "lng": -111.5262,
      "event_time_local": "2025/04/11 23:10:26 MDT",
      "event_time_epoch": 1744434626.36,
      "event_time_utc": "2025/04/12 05:10:26 UTC",
      "depth_mi": 4.72,
      "depth_km": 7.6,
      "version": "n/a",
      "etype": "le"
    }
  },
  {
    "event": {
      "evid": "90078693",
      "auth": "mb",
      "magnitude": 0.4,
      "lat": 44.6683,
      "lng": -111.8598,
      "event_time_local": "2025/04/11 21:47:52 MDT",
      "event_time_epoch": 1744429672.77,
      "event_time_utc": "2025/04/12 03:47:52 UTC",
      "depth_mi": 6.04,
      "depth_km": 9.72,
      "version": "n/a",
      "etype": "le"
    }
  },
  {
    "event": {
      "evid": "d0012wfj",
      "auth": "us",
      "magnitude": 2.4,
      "lat": 45.3306,
      "lng": -112.6263,
      "event_time_local": "2025/04/11 21:08:24 MDT",
      "event_time_epoch": 1744427304.566,
      "event_time_utc": "2025/04/12 03:08:24 UTC",
      "depth_mi": 5.38,
      "depth_km": 8.67,
      "version": "n/a",
      "etype": "le"
    }
  },
  {
    "event": {
      "evid": "90078123",
      "auth": "mb",
      "magnitude": 0.2,
      "lat": 44.8133,
      "lng": -111.4273,
      "event_time_local": "2025/04/11 20:56:25 MDT",
      "event_time_epoch": 1744426585.41,
      "event_time_utc": "2025/04/12 02:56:25 UTC",
      "depth_mi": 6.94,
      "depth_km": 11.18,
      "version": "n/a",
      "etype": "le"
    }
  },
  {
    "event": {
      "evid": "90078083",
      "auth": "mb",
      "magnitude": 1.6,
      "lat": 44.3363,
      "lng": -114.8187,
      "event_time_local": "2025/04/11 10:29:00 MDT",
      "event_time_epoch": 1744388940.89,
      "event_time_utc": "2025/04/11 16:29:00 UTC",
      "depth_mi": 4.61,
      "depth_km": 7.43,
      "version": "n/a",
      "etype": "le"
    }
  },
  {
    "event": {
      "evid": "90078053",
      "auth": "mb",
      "magnitude": 0.8,
      "lat": 44.7155,
      "lng": -112.0283,
      "event_time_local": "2025/04/11 09:13:05 MDT",
      "event_time_epoch": 1744384385.27,
      "event_time_utc": "2025/04/11 15:13:05 UTC",
      "depth_mi": 3.11,
      "depth_km": 5.0,
      "version": "n/a",
      "etype": "le"
    }
  },
  {
    "event": {
      "evid": "90077948",
      "auth": "mb",
      "magnitude": 0.9,
      "lat": 44.8652,
      "lng": -111.4923,
      "event_time_local": "2025/04/10 20:20:31 MDT",
      "event_time_epoch": 1744338031.3,
      "event_time_utc": "2025/04/11 02:20:31 UTC",
      "depth_mi": 4.71,
      "depth_km": 7.59,
      "version": "n/a",
      "etype": "le"
    }
  },
  {
    "event": {
      "evid": "90077918",
      "auth": "mb",
      "magnitude": 0.9,
      "lat": 45.0277,
      "lng": -112.4812,
      "event_time_local": "2025/04/10 14:35:31 MDT",
      "event_time_epoch": 1744317331.85,
      "event_time_utc": "2025/04/10 20:35:31 UTC",
      "depth_mi": 3.11,
      "depth_km": 5.0,
      "version": "n/a",
      "etype": "le"
    }
  },
  {
    "event": {
      "evid": "6000q57b",
      "auth": "us",
      "magnitude": 2.3,
      "lat": 44.3151,
      "lng": -115.1521,
      "event_time_local": "2025/04/10 12:23:03 MDT",
      "event_time_epoch": 1744309383.992,
      "event_time_utc": "2025/04/10 18:23:03 UTC",
      "depth_mi": 6.21,
      "depth_km": 10.0,
      "version": "n/a",
      "etype": "le"
    }
  },
  {
    "event": {
      "evid": "90077938",
      "auth": "mb",
      "magnitude": 0.3,
      "lat": 44.8355,
      "lng": -111.4652,
      "event_time_local": "2025/04/10 10:40:37 MDT",
      "event_time_epoch": 1744303237.65,
      "event_time_utc": "2025/04/10 16:40:37 UTC",
      "depth_mi": 4.61,
      "depth_km": 7.43,
      "version": "n/a",
      "etype": "le"
    }
  },
  {
    "event": {
      "evid": "90077888",
      "auth": "mb",
      "magnitude": 0.7,
      "lat": 44.5183,
      "lng": -114.2122,
      "event_time_local": "2025/04/10 09:09:30 MDT",
      "event_time_epoch": 1744297770.59,
      "event_time_utc": "2025/04/10 15:09:30 UTC",
      "depth_mi": 2.48,
      "depth_km": 4.0,
      "version": "n/a",
      "etype": "le"
    }
  },
  {
    "event": {
      "evid": "90077803",
      "auth": "mb",
      "magnitude": 0.6,
      "lat": 45.9867,
      "lng": -111.4997,
      "event_time_local": "2025/04/10 04:51:49 MDT",
      "event_time_epoch": 1744282309.59,
      "event_time_utc": "2025/04/10 10:51:49 UTC",
      "depth_mi": 3.12,
      "depth_km": 5.03,
      "version": "n/a",
      "etype": "le"
    }
  },
  {
    "event": {
      "evid": "90077798",
      "auth": "mb",
      "magnitude": 0.4,
      "lat": 44.8275,
      "lng": -111.5017,
      "event_time_local": "2025/04/10 01:04:42 MDT",
      "event_time_epoch": 1744268682.46,
      "event_time_utc": "2025/04/10 07:04:42 UTC",
      "depth_mi": 4.63,
      "depth_km": 7.46,
      "version": "n/a",
      "etype": "le"
    }
  },
  {
    "event": {
      "evid": "90077933",
      "auth": "mb",
      "magnitude": 0.1,
      "lat": 44.6923,
      "lng": -112.0352,
      "event_time_local": "2025/04/09 23:59:23 MDT",
      "event_time_epoch": 1744264763.84,
      "event_time_utc": "2025/04/10 05:59:23 UTC",
      "depth_mi": 3.14,
      "depth_km": 5.05,
      "version": "n/a",
      "etype": "le"
    }
  },
  {
    "event": {
      "evid": "90077773",
      "auth": "mb",
      "magnitude": 0.7,
      "lat": 44.8287,
      "lng": -111.4932,
      "event_time_local": "2025/04/09 21:32:46 MDT",
      "event_time_epoch": 1744255966.79,
      "event_time_utc": "2025/04/10 03:32:46 UTC",
      "depth_mi": 5.73,
      "depth_km": 9.23,
      "version": "n/a",
      "etype": "le"
    }
  },
  {
    "event": {
      "evid": "90077928",
      "auth": "mb",
      "magnitude": 0.1,
      "lat": 44.8748,
      "lng": -111.4642,
      "event_time_local": "2025/04/09 21:30:03 MDT",
      "event_time_epoch": 1744255803.04,
      "event_time_utc": "2025/04/10 03:30:03 UTC",
      "depth_mi": 5.77,
      "depth_km": 9.29,
      "version": "n/a",
      "etype": "le"
    }
  }
]
